Auto_Gradient_Boosting/__init__.py
Auto_Gradient_Boosting/main.py
Auto_Gradient_Boosting-1.0.0.dist-info/LICENSE
Auto_Gradient_Boosting-1.0.0.dist-info/METADATA
Auto_Gradient_Boosting-1.0.0.dist-info/WHEEL
Auto_Gradient_Boosting-1.0.0.dist-info/top_level.txt
Auto_Gradient_Boosting-1.0.0.dist-info/RECORD
